codeit/__init__.py
codeit/codeit.py
codeit/codeitHelp.py
codeit/codeitInit.py
codeit/codeitMeta.py
cxit-1.0.3.dist-info/LICENSE
cxit-1.0.3.dist-info/METADATA
cxit-1.0.3.dist-info/WHEEL
cxit-1.0.3.dist-info/entry_points.txt
cxit-1.0.3.dist-info/top_level.txt
cxit-1.0.3.dist-info/RECORD
