Metadata-Version: 2.1
Name: cxit
Version: 1.0.3
Summary: A CLI tool to create CPP files for any contest
Home-page: https://github.com/Arch2x/codeit
Author: Aadhitya A
Author-email: aadhitya864@gmail.com
License: MIT License
Platform: UNKNOWN
Classifier: Intended Audience :: Developers
Classifier: License :: OSI Approved :: MIT License
Classifier: Programming Language :: Python :: 3.7
Requires-Python: >=3.5
Requires-Dist: clint
